scriptslib/__init__.py
scriptslib/test_wikimedia.py
scriptslib/wikimedia.py
tests/__init__.py
tests/utilities.py
tests/wikimedia_tests.py
scriptslib-0.0.3.dist-info/METADATA
scriptslib-0.0.3.dist-info/WHEEL
scriptslib-0.0.3.dist-info/top_level.txt
scriptslib-0.0.3.dist-info/RECORD
